Metadata-Version: 1.1
Name: aiocall
Version: 0.2
Summary: The missing call methods for python asyncio
Home-page: http://github.com/waldhol/aiocall
Author: Holger Waldmann
Author-email: holger.waldmann@web.de
License: Public Domain
Platform: UNKNOWN
Classifier: Development Status :: 3 - Alpha
Classifier: Intended Audience :: Developers
Classifier: License :: Public Domain
Classifier: Programming Language :: Python :: 3
Classifier: Programming Language :: Python :: 3.5
